{
  "title": "Piku",
  "description": "Learn about Piku and its features",
  "details": {
    "intro": {
      "text": "intro.md"
    },
    "steps": [
      {
        "title": "Step 1: Install Piku",
        "text": "install/install.md",
        "foreground": "install/foreground.sh",
        "verify": "install/verify.sh"
      },
      {
        "title": "Step 2: Deploying a clojure application",
        "text": "first-deploy/first-deploy.md",
        "verify": "first-deploy/verify.sh"
      },
      {
        "title": "Step 3: Change Environment Variables",
        "text": "change-env/change-env.md",
        "verify": "change-env/verify.sh"
      },
      {
        "title": "Step 4: Add Plugins",
        "text": "add-plugin/add-plugin.md"
      }
    ],
    "finish": {
      "text": "finish.md"
    }
  },
  "backend": {
    "imageid": "ubuntu"
  }
}
